README.txt
setup.py
serialXfer/XMODEM.py
serialXfer/YMODEM.py
serialXfer/__init__.py
serialXfer/version.py
serialXfer.egg-info/PKG-INFO
serialXfer.egg-info/SOURCES.txt
serialXfer.egg-info/dependency_links.txt
serialXfer.egg-info/top_level.txt