Metadata-Version: 1.0
Name: serialXfer
Version: 0.3
Summary: Ancient serial file transfer protocols in Python
Home-page: http://pypi.python.org/pypi/serialXfer
Author: Jason Morgan
Author-email: pypi@cropwell.net
License: BSD
Keywords: XMODEM YMODEM ZMODEM Kermit Serial
Platform: any
Classifier: Development Status :: 3 - Alpha
Classifier: Topic :: Software Development :: Libraries :: Python Modules
Classifier: Intended Audience :: Developers
Classifier: License :: Other/Proprietary License
Classifier: Operating System :: OS Independent
Classifier: Programming Language :: Python
